jiagu/__init__.py
jiagu/__main__.py
jiagu/analyze.py
jiagu/bilstm_crf.py
jiagu/findword.py
jiagu/mmseg.py
jiagu/textrank.py
jiagu/utils.py
jiagu/data/Trie.pkl
jiagu/data/chars.dic
jiagu/data/jiagu.dict
jiagu/model/cws.model
jiagu/model/ner.model
jiagu/model/pos.model
jiagu-0.1.3.dist-info/METADATA
jiagu-0.1.3.dist-info/WHEEL
jiagu-0.1.3.dist-info/top_level.txt
jiagu-0.1.3.dist-info/RECORD
