Metadata-Version: 2.1
Name: jiagu
Version: 0.1.3
Summary: Jiagu Natural Language Processing
Home-page: https://github.com/ownthink/Jiagu
Author: Yener(Zheng Wenyu)
Author-email: help@ownthink.com
License: MIT
Platform: UNKNOWN
Requires-Dist: tensorflow (>=1.4.0)
Requires-Dist: numpy (>=1.12.1)
Requires-Dist: networkx (>=2.1)
